README.md
setup.cfg
setup.py
Convert2PDF/ConvertToPDF.py
Convert2PDF/__init__.py
Convert2PDF.egg-info/PKG-INFO
Convert2PDF.egg-info/SOURCES.txt
Convert2PDF.egg-info/dependency_links.txt
Convert2PDF.egg-info/requires.txt
Convert2PDF.egg-info/top_level.txt