Metadata-Version: 2.1
Name: Convert2PDF
Version: 0.1
Summary: Convert from different file formats to PDF format.
Home-page: https://github.com/ashfaque/Convert2PDF
Author: Ashfaque Alam
Author-email: ashfaquealam496@yahoo.com
License: GNU GPLv3
Download-URL: https://github.com/ashfaque/Convert2PDF/archive/refs/tags/v_01.tar.gz
Keywords: ASHFAQUE,ASHFAQUE ALAM,CONVERT,PDF,CONVERT TO PDF
Platform: UNKNOWN
Classifier: Development Status :: 5 - Production/Stable
Classifier: Intended Audience :: Developers
Classifier: Topic :: Software Development :: Build Tools
Classifier: License :: OSI Approved :: GNU General Public License (GPL)
Classifier: Programming Language :: Python :: 3
Classifier: Programming Language :: Python :: 3.5
Classifier: Programming Language :: Python :: 3.6
Classifier: Programming Language :: Python :: 3.7
Classifier: Programming Language :: Python :: 3.8
Classifier: Programming Language :: Python :: 3.9
Classifier: Programming Language :: Python :: 3.10
